README.md
setup.py
pyaos/__init__.py
pyaos/aosencryfunc.py
pyaos/base.py
pyaos/chain.py
pyaos/wallet.py
pyaos.egg-info/PKG-INFO
pyaos.egg-info/SOURCES.txt
pyaos.egg-info/dependency_links.txt
pyaos.egg-info/top_level.txt